rstats_logreader/__init__.py
rstats_logreader/cli.py
rstats_logreader/reader.py
rstats_logreader-3.1.2.dist-info/LICENSE.md
rstats_logreader-3.1.2.dist-info/METADATA
rstats_logreader-3.1.2.dist-info/WHEEL
rstats_logreader-3.1.2.dist-info/entry_points.txt
rstats_logreader-3.1.2.dist-info/top_level.txt
rstats_logreader-3.1.2.dist-info/zip-safe
rstats_logreader-3.1.2.dist-info/RECORD
