Metadata-Version: 2.1
Name: rstats-logreader
Version: 3.1.2
Summary: Parse RStats-format bandwidth logfiles and perform simple analysis/aggregation.
Author-email: Jeremy Brown <mischif@users.noreply.github.com>
License: # The Prosperity Public License 3.0.0        
Project-URL: repository, https://github.com/mischif/rstats-logreader
Classifier: Development Status :: 5 - Production/Stable
Classifier: Environment :: Console
Classifier: Intended Audience :: Information Technology
Classifier: Operating System :: OS Independent
Classifier: Programming Language :: Python :: 3
Classifier: Programming Language :: Python :: 3.8
Classifier: Programming Language :: Python :: 3.9
Classifier: Programming Language :: Python :: 3.10
Classifier: Topic :: System :: Networking
Classifier: Topic :: System :: Networking :: Monitoring
Classifier: Topic :: Utilities
Requires-Python: ~=3.8
License-File: LICENSE.md
Provides-Extra: test
Requires-Dist: codecov ; extra == 'test'
Requires-Dist: coverage[toml] ; extra == 'test'
Requires-Dist: hypothesis ; extra == 'test'
Requires-Dist: hypothesis-pytest ; extra == 'test'
Requires-Dist: pytest (>=6.0) ; extra == 'test'
Requires-Dist: pytest-cov ; extra == 'test'
